setup.py
micropython_urllib.urequest.egg-info/PKG-INFO
micropython_urllib.urequest.egg-info/SOURCES.txt
micropython_urllib.urequest.egg-info/dependency_links.txt
micropython_urllib.urequest.egg-info/top_level.txt
urllib/urequest.py