Metadata-Version: 1.0
Name: micropython-urllib.urequest
Version: 0.5.1
Summary: urllib.urequest module for MicroPython
Home-page: https://github.com/micropython/micropython-lib
Author: micropython-lib Developers
Author-email: micro-python@googlegroups.com
License: MIT
Platform: UNKNOWN
